CHANGES.txt
LICENSE
MANIFEST.in
README.rst
kaninipycs.py
setup.cfg
setup.py
docs/Makefile
docs/advanced.rst
docs/api.rst
docs/conf.py
docs/developer.rst
docs/index.rst
docs/intro.rst
docs/make.bat
kaninipycs.egg-info/PKG-INFO
kaninipycs.egg-info/SOURCES.txt
kaninipycs.egg-info/dependency_links.txt
kaninipycs.egg-info/entry_points.txt
kaninipycs.egg-info/not-zip-safe
kaninipycs.egg-info/top_level.txt
testsuite/E10.py
testsuite/E11.py
testsuite/E12.py
testsuite/E12not.py
testsuite/E20.py
testsuite/E21.py
testsuite/E22.py
testsuite/E23.py
testsuite/E24.py
testsuite/E25.py
testsuite/E26.py
testsuite/E27.py
testsuite/E30.py
testsuite/E30not.py
testsuite/E40.py
testsuite/E50.py
testsuite/E70.py
testsuite/E71.py
testsuite/E72.py
testsuite/E73.py
testsuite/E74.py
testsuite/E90.py
testsuite/W19.py
testsuite/W29.py
testsuite/W39.py
testsuite/W60.py
testsuite/__init__.py
testsuite/crlf.py
testsuite/latin-1.py
testsuite/noqa.py
testsuite/python3.py
testsuite/python310.py
testsuite/python311.py
testsuite/python35.py
testsuite/python38.py
testsuite/support.py
testsuite/test_all.py
testsuite/test_api.py
testsuite/test_blank_lines.py
testsuite/test_parser.py
testsuite/test_shell.py
testsuite/test_util.py
testsuite/utf-8-bom.py
testsuite/utf-8.py